termlogger/__init__.py
termlogger/__main__.py
termlogger/adif.py
termlogger/app.py
termlogger/callsign.py
termlogger/config.py
termlogger/database.py
termlogger/models.py
termlogger/termlogger.css
termlogger/modes/__init__.py
termlogger/modes/base.py
termlogger/modes/contest.py
termlogger/modes/fieldday.py
termlogger/modes/pota.py
termlogger/screens/__init__.py
termlogger/screens/file_picker.py
termlogger/screens/help.py
termlogger/screens/log_browser.py
termlogger/screens/log_manager.py
termlogger/screens/main.py
termlogger/screens/mode_setup.py
termlogger/screens/settings.py
termlogger/services/__init__.py
termlogger/services/clublog.py
termlogger/services/dx_cluster.py
termlogger/services/flexradio.py
termlogger/services/pota_parks.py
termlogger/services/pota_spots.py
termlogger/services/qrz_logbook.py
termlogger/services/rigctld.py
termlogger/services/udp_log_server.py
termlogger/widgets/__init__.py
termlogger/widgets/extended_fields.py
termlogger/widgets/qso_entry.py
termlogger/widgets/qso_table.py
termlogger/widgets/spots_table.py
termlogger/widgets/tune_dialog.py
termlogger-26.1.2.dist-info/METADATA
termlogger-26.1.2.dist-info/WHEEL
termlogger-26.1.2.dist-info/entry_points.txt
termlogger-26.1.2.dist-info/licenses/LICENSE
termlogger-26.1.2.dist-info/RECORD
