Metadata-Version: 2.4
Name: termlogger
Version: 26.1.2
Summary: A terminal-based amateur radio logging application
Author: TermLogger Contributors
License-Expression: MIT
License-File: LICENSE
Keywords: amateur-radio,ham-radio,logging,terminal,tui
Classifier: Development Status :: 3 - Alpha
Classifier: Environment :: Console
Classifier: Intended Audience :: End Users/Desktop
Classifier: License :: OSI Approved :: MIT License
Classifier: Operating System :: OS Independent
Classifier: Programming Language :: Python :: 3
Classifier: Programming Language :: Python :: 3.11
Classifier: Programming Language :: Python :: 3.12
Classifier: Topic :: Communications :: Ham Radio
Requires-Python: >=3.11
Requires-Dist: httpx
Requires-Dist: pydantic>=2.0
Requires-Dist: python-dateutil
Requires-Dist: textual>=0.47.0
Requires-Dist: xmltodict
Provides-Extra: build
Requires-Dist: build; extra == 'build'
Requires-Dist: pyinstaller>=6.0; extra == 'build'
Provides-Extra: dev
Requires-Dist: pytest; extra == 'dev'
Requires-Dist: pytest-asyncio; extra == 'dev'
Requires-Dist: ruff; extra == 'dev'
Requires-Dist: textual-dev; extra == 'dev'
